db_extract/__init__.py
db_extract/constants.py
db_extract/models.py
db_extract/utilities.py
db_extract-0.2.dist-info/LICENSE
db_extract-0.2.dist-info/METADATA
db_extract-0.2.dist-info/WHEEL
db_extract-0.2.dist-info/top_level.txt
db_extract-0.2.dist-info/RECORD
