Metadata-Version: 2.1
Name: db-extract
Version: 0.2
Summary: A package that can perform on-the-fly denormalization
Home-page: https://github.com/sareeneng/db_extract/
Author: Sareen Shah
Author-email: shah.sareen@gmail.com
License: UNKNOWN
Platform: UNKNOWN
Classifier: Programming Language :: Python :: 3
Classifier: License :: OSI Approved :: MIT License
Classifier: Operating System :: OS Independent
Requires-Dist: appdirs (>=1.4.3)
Requires-Dist: networkx (>=2.4)
Requires-Dist: pandas (>=1.0.1)
Requires-Dist: pyodbc (>=4.0.30)
Requires-Dist: sqlalchemy-utils (>=0.36.1)
Requires-Dist: sqlalchemy (>=1.3.13)
